deeplib/__init__.py
deeplib_ml-0.1.0.dist-info/METADATA
deeplib_ml-0.1.0.dist-info/WHEEL
deeplib_ml-0.1.0.dist-info/top_level.txt
deeplib_ml-0.1.0.dist-info/RECORD
